[
  { "question": "Apa saja gejala Diabetes Melitus?" },
  { "question": "Bagaimana cara mendiagnosis Hipertensi?" },
  { "question": "Apa penyebab dari Asma?" },
  { "question": "Bagaimana cara mengobati Demam Berdarah?" },
  { "question": "Apa saja gejala COVID-19?" },
  { "question": "Apakah Stroke bisa disembuhkan?" },
  { "question": "Apa komplikasi yang mungkin terjadi akibat Penyakit Jantung Koroner?" },
  { "question": "Bagaimana cara mencegah TBC?" },
  { "question": "Apakah Maag bisa menjadi penyakit kronis?" },
  { "question": "Bagaimana cara mendiagnosis Kanker Payudara?" },
  { "question": "Apa saja gejala Gagal Ginjal?" },
  { "question": "Apa penyebab dari Kanker Paru-paru?" },
  { "question": "Bagaimana cara mengobati GERD?" },
  { "question": "Apakah Anemia bisa menyebabkan kelelahan kronis?" },
  { "question": "Apa itu Penyakit Liver dan bagaimana cara mendeteksinya?" },
  { "question": "Apa penyebab dari Katarak?" },
  { "question": "Bagaimana cara mendiagnosis Osteoporosis?" },
  { "question": "Apa saja gejala Penyakit Lupus?" },
  { "question": "Apakah Vertigo berbahaya?" },
  { "question": "Bagaimana cara mengobati Infeksi Saluran Kemih?" },
  { "question": "Apa komplikasi yang mungkin terjadi akibat Hepatitis B?" },
  { "question": "Apa itu Psoriasis dan apa penyebabnya?" },
  { "question": "Apakah ISPA bisa sembuh total?" },
  { "question": "Bagaimana cara mencegah Kanker Serviks?" },
  { "question": "Apa perbedaan antara Flu dan Pilek biasa?" }
]
